django_flexible_reports-0.2.10.dist-info/DESCRIPTION.rst
django_flexible_reports-0.2.10.dist-info/METADATA
django_flexible_reports-0.2.10.dist-info/RECORD
django_flexible_reports-0.2.10.dist-info/WHEEL
django_flexible_reports-0.2.10.dist-info/metadata.json
django_flexible_reports-0.2.10.dist-info/top_level.txt
flexible_reports/__init__.py
flexible_reports/apps.py
flexible_reports/constants.py
flexible_reports/urls.py
flexible_reports/utils.py
flexible_reports/views.py
flexible_reports/adapters/__init__.py
flexible_reports/adapters/django_tables2.py
flexible_reports/admin/__init__.py
flexible_reports/admin/datasource.py
flexible_reports/admin/helpers.py
flexible_reports/admin/report.py
flexible_reports/admin/table.py
flexible_reports/locale/pl/LC_MESSAGES/django.mo
flexible_reports/locale/pl/LC_MESSAGES/django.po
flexible_reports/migrations/0001_initial.py
flexible_reports/migrations/0002_auto_20170823_2225.py
flexible_reports/migrations/0003_table_attrs.py
flexible_reports/migrations/0004_auto_20170823_2342.py
flexible_reports/migrations/0005_column_attrs.py
flexible_reports/migrations/0006_default_ordering.py
flexible_reports/migrations/0007_sort_desc.py
flexible_reports/migrations/0008_auto_20171025_0553.py
flexible_reports/migrations/0009_auto_20171025_0558.py
flexible_reports/migrations/0010_auto_20171026_0340.py
flexible_reports/migrations/0011_alter_reportelement_options_alter_column_attrs_and_more.py
flexible_reports/migrations/__init__.py
flexible_reports/models/__init__.py
flexible_reports/models/behaviors.py
flexible_reports/models/column.py
flexible_reports/models/datasource.py
flexible_reports/models/report.py
flexible_reports/models/table.py
flexible_reports/models/validators.py
flexible_reports/static/css/flexible_reports.css
flexible_reports/static/js/flexible_reports.js
flexible_reports/templates/flexible_reports/report.html
flexible_reports/templatetags/__init__.py
flexible_reports/templatetags/flexible_reports_tags.py
