Metadata-Version: 2.0
Name: django-flexible-reports
Version: 0.2.10
Summary: A framework for report generation in Django
Home-page: https://github.com/mpasternak/django-flexible-reports
Author: Michał Pasternak
Author-email: michal.dtz@gmail.com
License: MIT
Keywords: django-flexible-reports
Classifier: Development Status :: 3 - Alpha
Classifier: Framework :: Django
Classifier: Framework :: Django :: 1.10
Classifier: Intended Audience :: Developers
Classifier: License :: OSI Approved :: BSD License
Classifier: Natural Language :: English
Classifier: Programming Language :: Python :: 3.6
License-File: LICENSE
License-File: AUTHORS.rst
Requires-Dist: Django
Requires-Dist: bleach (>=2.1.1)
Requires-Dist: django-dsl (>=0.1.12)
Requires-Dist: django-tables2 (>=1.16.0)
Requires-Dist: lxml (>=3.8.0)
Requires-Dist: pypandoc (>=1.4)
Requires-Dist: tablib (>=0.11.5)
